odoo10_addon_website_sale_order_type-10.0.1.0.0.99.dev4-py3.8-nspkg.pth
odoo/addons/website_sale_order_type/README.rst
odoo/addons/website_sale_order_type/__init__.py
odoo/addons/website_sale_order_type/__manifest__.py
odoo/addons/website_sale_order_type/i18n/website_sale_order_type.pot
odoo/addons/website_sale_order_type/models/__init__.py
odoo/addons/website_sale_order_type/models/sale_order.py
odoo/addons/website_sale_order_type/readme/CONTRIBUTORS.rst
odoo/addons/website_sale_order_type/readme/DESCRIPTION.rst
odoo/addons/website_sale_order_type/readme/USAGE.rst
odoo/addons/website_sale_order_type/static/description/icon.png
odoo/addons/website_sale_order_type/static/description/index.html
odoo/addons/website_sale_order_type/tests/__init__.py
odoo/addons/website_sale_order_type/tests/test_website_sale_order_type.py
odoo10_addon_website_sale_order_type-10.0.1.0.0.99.dev4.dist-info/METADATA
odoo10_addon_website_sale_order_type-10.0.1.0.0.99.dev4.dist-info/WHEEL
odoo10_addon_website_sale_order_type-10.0.1.0.0.99.dev4.dist-info/namespace_packages.txt
odoo10_addon_website_sale_order_type-10.0.1.0.0.99.dev4.dist-info/top_level.txt
odoo10_addon_website_sale_order_type-10.0.1.0.0.99.dev4.dist-info/RECORD
