Metadata-Version: 2.1
Name: odoo10-addon-website-sale-order-type
Version: 10.0.1.0.0.99.dev4
Summary: This module allows sale_order_type to work with website_sale.
Home-page: https://github.com/OCA/e-commerce/tree/10.0/website_sale_order_type
Author: Agile Business Group, Odoo Community Association (OCA)
Author-email: support@odoo-community.org
License: AGPL-3
Platform: UNKNOWN
Classifier: Programming Language :: Python
Classifier: Framework :: Odoo
Classifier: Framework :: Odoo :: 10.0
Classifier: License :: OSI Approved :: GNU Affero General Public License v3
Classifier: Development Status :: 4 - Beta
Requires-Python: ~=2.7
Requires-Dist: odoo10-addon-sale-order-type
Requires-Dist: odoo <10.1dev,>=10.0
